easymde/__init__.py
easymde/fields.py
easymde/utils.py
easymde/widgets.py
easymde/static/easymde/easymde.init.js
easymde/static/easymde/easymde.min.css
easymde/static/easymde/easymde.min.js
django_easymde-1.0.4.dist-info/METADATA
django_easymde-1.0.4.dist-info/WHEEL
django_easymde-1.0.4.dist-info/top_level.txt
django_easymde-1.0.4.dist-info/RECORD
