Metadata-Version: 2.1
Name: django-easymde
Version: 1.0.4
Summary: django-easymde is a WYSIWYG markdown editor for Django
Home-page: https://github.com/WPI-LNL/django-easymde
Author: Benjamin Antupit
Author-email: b@antupit.com
License: MIT
Keywords: django,admin,wysiwyg,markdown,editor,easymde
Classifier: Development Status :: 5 - Production/Stable
Classifier: Environment :: Web Environment
Classifier: Framework :: Django
Classifier: Intended Audience :: Developers
Classifier: License :: OSI Approved :: BSD License
Classifier: Operating System :: OS Independent
Classifier: Programming Language :: Python
Requires-Dist: setuptools
